Metadata-Version: 2.1
Name: strprogressbar
Version: 1.0
Summary: A simple python package to create Progress bars as Strings
Home-page: https://github.com/SDeVuyst/strprogressbar
Download-URL: https://github.com/SDeVuyst/strprogressbar/archive/refs/tags/v_1.0.tar.gz
Author: SDeVuyst
Author-email: 
License: GNU General Public License v3 (GPLv3)
Keywords: string,progressbar,progress,bar
Classifier: Development Status :: 5 - Production/Stable
Classifier: Intended Audience :: Developers
Classifier: Operating System :: Microsoft :: Windows :: Windows 10
Classifier: License :: OSI Approved :: GNU General Public License v3 (GPLv3)
Classifier: Programming Language :: Python :: 3
License-File: LICENSE
